setup.py
staste/__init__.py
staste/axis.py
staste/dateaxis.py
staste/metrica.py
staste/middleware.py
staste/models.py
staste/tests.py
staste/utils.py
staste/views.py
staste.egg-info/PKG-INFO
staste.egg-info/SOURCES.txt
staste.egg-info/dependency_links.txt
staste.egg-info/top_level.txt
staste/charts/__init__.py
staste/charts/views.py