Metadata-Version: 1.0
Name: staste
Version: 0.1.1f
Summary: Slightly complicated event tracker for your Django website.
Home-page: http://staste.unfoldthat.com/
Author: Valentin Golev
Author-email: v.golev@gmail.com
License: UNKNOWN
Platform: UNKNOWN
